{
  "schema": "war3-item-editor-data/v1",
  "id": "rugt",
  "displayName": "神秘手套",
  "identity": {
    "race": "neutral",
    "class": "Miscellaneous",
    "level": 0,
    "legacyLevel": 0,
    "scriptName": "RunedGauntlets"
  },
  "assets": {
    "art": [
      {
        "requestedPath": "ReplaceableTextures\\CommandButtons\\BTNImprovedUnholyStrength.blp",
        "resolvedPath": "ReplaceableTextures\\CommandButtons\\BTNImprovedUnholyStrength.blp",
        "sourceLayer": "roc",
        "godotPath": "textures/replaceabletextures/commandbuttons/btnimprovedunholystrength.png"
      }
    ],
    "worldModel": [
      {
        "requestedPath": "Objects\\InventoryItems\\TreasureChest\\treasurechest.mdl",
        "resolvedPath": "Objects\\InventoryItems\\treasurechest\\treasurechest.mdx",
        "sourceLayer": "tft",
        "godotPath": "models/objects/inventoryitems/treasurechest/treasurechest.glb"
      }
    ]
  },
  "summary": {
    "abilities": [
      "AId3",
      "AIs3"
    ],
    "cooldownAbilityId": "AIab",
    "ignoreCooldown": false,
    "priority": 0,
    "usable": false,
    "perishable": false,
    "droppable": true,
    "pawnable": true,
    "sellable": true,
    "randomDrop": false,
    "powerup": false,
    "droppedWhenCarrierDies": false,
    "stockMaximum": 1,
    "stockReplenishSeconds": 180,
    "stockStartDelaySeconds": 0,
    "goldCost": 725,
    "lumberCost": 0,
    "hitPoints": 75,
    "armorType": "Wood",
    "scale": 1,
    "selectionSize": 0,
    "buttonPosition": [],
    "requirements": [],
    "hotkey": "R",
    "tooltip": "购买神秘手套(|cffffcc00R|r)",
    "extendedTooltip": "\"当携带的时候增加英雄3点的力量和护甲。\"",
    "description": "\"能增加力量和护甲。\""
  },
  "editorData": {
    "itemID": "rugt",
    "comment": "Runed Gauntlets",
    "version": "1",
    "class": "Miscellaneous",
    "Level": "0",
    "oldLevel": "0",
    "abilList": "AId3,AIs3",
    "cooldownID": "AIab",
    "ignoreCD": "0",
    "uses": "-",
    "prio": "0",
    "usable": "0",
    "perishable": "0",
    "droppable": "1",
    "pawnable": "1",
    "sellable": "1",
    "pickRandom": "0",
    "powerup": "0",
    "drop": "0",
    "stockMax": "1",
    "stockRegen": "180",
    "stockStart": "0",
    "goldcost": "725",
    "lumbercost": "0",
    "HP": "75",
    "morph": "0",
    "armor": "Wood",
    "file": "Objects\\InventoryItems\\TreasureChest\\treasurechest.mdl",
    "scale": "1",
    "colorR": "255",
    "colorG": "255",
    "colorB": "255",
    "InBeta": "0",
    "scriptname": "RunedGauntlets",
    "selSize": "0"
  },
  "profile": {
    "Art": "ReplaceableTextures\\CommandButtons\\BTNImprovedUnholyStrength.blp",
    "Name": "神秘手套",
    "Hotkey": "R",
    "Tip": "购买神秘手套(|cffffcc00R|r)",
    "Ubertip": "\"当携带的时候增加英雄3点的力量和护甲。\"",
    "Description": "\"能增加力量和护甲。\""
  },
  "provenance": {
    "sourceFiles": [
      "extracted/raw/classic/patch/Units/ItemData.slk",
      "extracted/raw/classic/patch/Units/ItemFunc.txt",
      "extracted/raw/classic/patch/Units/ItemStrings.txt",
      "extracted/raw/classic/tft-locale/Units/ItemStrings.txt",
      "extracted/raw/classic/tft/Units/ItemData.slk",
      "extracted/raw/classic/tft/Units/ItemFunc.txt"
    ]
  }
}
