{
  "schema": "war3-buff-effect-editor-data/v1",
  "id": "Bshs",
  "displayName": "Bshs",
  "identity": {
    "baseCode": "Bshs",
    "race": "other",
    "effect": false,
    "editorVisible": true,
    "profileOnly": false
  },
  "assets": {
    "buffArt": [
      {
        "requestedPath": "ReplaceableTextures\\CommandButtons\\BTNWandOfShadowSight.blp",
        "resolvedPath": "ReplaceableTextures\\CommandButtons\\BTNWandOfShadowSight.blp",
        "sourceLayer": "tft",
        "godotPath": "textures/replaceabletextures/commandbuttons/btnwandofshadowsight.png"
      }
    ]
  },
  "summary": {
    "levels": []
  },
  "presentation": {
    "casterAttachments": [],
    "targetAttachments": [],
    "specialAttachments": []
  },
  "referencedBy": [
    {
      "abilityId": "Ashs",
      "level": 1,
      "kind": "buff",
      "race": "other"
    }
  ],
  "editorData": {
    "alias": "Bshs",
    "code": "Bshs",
    "comments": "ShadowSight            ",
    "isEffect": "0",
    "version": "1",
    "useInEditor": "1",
    "sort": "unit",
    "race": "other",
    "InBeta": "1"
  },
  "profile": {
    "Buffart": "ReplaceableTextures\\CommandButtons\\BTNWandOfShadowSight.blp",
    "Bufftip": "影子权杖",
    "Buffubertip": "\"该单位受到了影子权杖的作用; 因此其将暴露在敌人的视野之下。\""
  },
  "provenance": {
    "sourceFiles": [
      "extracted/raw/classic/patch/Units/AbilityBuffData.slk",
      "extracted/raw/classic/patch/Units/ItemAbilityFunc.txt",
      "extracted/raw/classic/patch/Units/ItemAbilityStrings.txt",
      "extracted/raw/classic/tft-locale/Units/ItemAbilityStrings.txt",
      "extracted/raw/classic/tft/Units/ItemAbilityFunc.txt"
    ]
  }
}
